[
    {
        "author": "Maria Popova",
        "description": "The week’s most interesting and inspiring articles across art, science, philosophy, creativity, children’s books, and other strands of our search for truth, beauty, and meaning.",
        "categories": [
            "Art",
            "Science",
            "Philosophy"
        ],
        "frequency": "Weekly",
        "image": "https://www.brainpickings.org/wp-content/themes/brainpickings/images/brain_pickings_icon@2x.png",
        "source": {
            "name": "Brainpickings",
            "url": "https://www.brainpickings.org/newsletter/"
        }
    },
    {
        "author": "Tim Ferriss",
        "description": "The five coolest things I’ve found (or explored) that week. It could include exclusive giveaways or chances to interact with me, books, gadgets, albums, articles, new hacks/tricks, and — of course — all sorts of weird stuff I dig up around the world.",
        "categories": [
            "Business",
            "Technology"
        ],
        "frequency": "Weekly",
        "image": "https://peterattiamd.com/wp-content/uploads/2018/06/TimFerrissShoot-186.jpg",
        "source": {
            "name": "Five-Bullet Friday",
            "url": "https://go.tim.blog/5-bullet-friday-1/"
        }
    },
    {
        "author": "Ryan Holiday",
        "description": "5 to 10 amazing books that I read, reviewed and think you’ll like. The goal of the newsletter is to recommend books that stick with you long after you’ve put them down—or better yet, change your life.",
        "categories": [
            "Books"
        ],
        "frequency": "Monthly",
        "image": "https://149366099.v2.pressablecdn.com/wp-content/uploads/2018/06/r-holiday-500px.jpg",
        "source": {
            "name": "Reading Recommendations",
            "url": "https://ryanholiday.net/reading-newsletter/"
        }
    },
    {
        "author": "Benedict Evans",
        "description": "My notes for the week on the news that actually matters and what it might mean.",
        "categories": [
            "Business",
            "Technology"
        ],
        "frequency": "Weekly",
        "image": "https://pbs.twimg.com/profile_images/845396356579508224/1ruiOPLI_400x400.jpg",
        "source": {
            "name": "Newsletter",
            "url": "https://www.ben-evans.com/"
        }
    },
    {
        "author": "NY Times",
        "description": "Wake Up With The Times, Anywhere in the World. What you need to know to start your day, each weekday morning.",
        "categories": [
            "News"
        ],
        "frequency": "Daily",
        "image": "https://static01.nyt.com/email-images/Newsletter%20Icons/Morning-Briefing.png",
        "source": {
            "name": "Morning Briefing",
            "url": "https://www.nytimes.com/interactive/2018/briefing/global-morning-briefing-newsletter-signup.html"
        }
    },
    {
        "author": "Robert Cottrell, Caroline Crampton",
        "description": "Every day we read hundreds of articles and select the best five for you to enjoy, so you'll always have something to read on the train and interesting things to say at dinner.",
        "categories": [
            "News",
            "General"
        ],
        "frequency": "Weekly",
        "image": "https://scontent-ort2-1.xx.fbcdn.net/v/t1.0-9/10262151_10153498700767475_3970334184715487679_n.jpg?_nc_cat=109&_nc_sid=85a577&_nc_ohc=EcJGNgWArjEAX_WXA1s&_nc_ht=scontent-ort2-1.xx&oh=eb7b09a2ffc81404d0643d6f8686292d&oe=5E94615E",
        "source": {
            "name": "The Browser",
            "url": "https://thebrowser.com/"
        }
    },
    {
        "author": "Kevin Kelly, Mark Frauenfelder, Claudia Dawson",
        "description": "A weekly newsletter that gives you 6 brief personal recommendations of cool stuff.",
        "categories": [
            "General"
        ],
        "frequency": "Weekly",
        "image": "https://s3.amazonaws.com/revue/profiles/images/000/014/381/thumb/ThumbReco.png",
        "source": {
            "name": "Recomendo",
            "url": "https://www.getrevue.co/profile/Recomendo"
        }
    },
    {
        "author": "Kevin Rose",
        "description": "Kevin's favorite articles, life and body hacks, videos, products, and odd obsessions.",
        "categories": [
            "General"
        ],
        "frequency": "Monthly",
        "image": "https://static.wixstatic.com/media/5cf308_3d44d7f1f10845ce8a94b5638faa8503~mv2.png",
        "source": {
            "name": "The Journal",
            "url": "https://www.kevinrose.com/newsletter"
        }
    },
    {
        "author": "Nathan Yau",
        "description": "Get the latest on visualization, statistics, and data.",
        "categories": [
            "Data"
        ],
        "frequency": "Weekly",
        "image": "https://i2.wp.com/flowingdata.com/wp-content/uploads/2014/10/logo-lone-square-600-5451c585_site_icon.png",
        "source": {
            "name": "FlowingData",
            "url": "https://flowingdata.com/newsletter/"
        }
    },
    {
        "author": "Hacker News",
        "description": "Since 2010, we've put out a weekly newsletter of the best articles on startups, technology, programming, and more.",
        "categories": [
            "Startups",
            "Technology"
        ],
        "frequency": "Weekly",
        "image": "https://image.winudf.com/v2/image/Y29tLmFwcGVuZ3Vpbi5oYWNrZXJuZXdzX2ljb25fMTUxODYyNDAxOV8wOTI/icon.png?w=170&fakeurl=1",
        "source": {
            "name": "Hacker News",
            "url": "https://hackernewsletter.com/"
        }
    },
    {
        "author": "Robinhood",
        "description": "The 3-minute newsletter with fresh takes on the financial news you need to start your day.",
        "categories": [
            "Business"
        ],
        "frequency": "Daily",
        "image": "https://megaphone-prod.s3.amazonaws.com/podcasts/6f5e0684-0f62-11e9-8892-c3999a92d94d/image/uploads_2F1572397783054-6o9dpywwwhw-d0dae8b553156c24ea5f76003bd5b130_2FSnacks%2BSquare%2BLogo.png",
        "source": {
            "name": "Robinhood Snacks",
            "url": "https://snacks.robinhood.com/"
        }
    },
    {
        "author": "Mark Manson",
        "description": "We all need a little attitude on Monday morning. It’s a way to start your week off with a bang. And fill yourself with ideas that could potentially change everything.",
        "categories": [
            "Self-Improvement"
        ],
        "frequency": "Weekly",
        "image": "https://media-exp1.licdn.com/dms/image/C4D0BAQHZjpFXaLQSnQ/company-logo_200_200/0?e=2159024400&v=beta&t=ZRqvMdS0g1YkJH3eAWKwRlHAU0K4TJ4aoZITC5MicEk",
        "source": {
            "name": "Motherf*ckin' Monday",
            "url": "https://markmanson.net/newsletter"
        }
    },
    {
        "author": "Shane Parrish",
        "description": "Our team scours the web and devours hundreds of books a year to bring you the very best of human thinking. No fluff. No noise. Just the most useful insights you can use today to sharpen your mind, make smarter decisions and live with more purpose.",
        "categories": [
            "Business",
            "General"
        ],
        "frequency": "Weekly",
        "image": "https://pbs.twimg.com/profile_images/1157029452146192391/LFWIz20B_400x400.jpg",
        "source": {
            "name": "Farnam Street",
            "url": "https://fs.blog/newsletter/"
        }
    },
    {
        "author": "James Clear",
        "description": "Every Thursday, I send out my “3-2-1” newsletter with 3 ideas from me, 2 quotes from others, and 1 question for you.",
        "categories": [
            "Self-Improvement"
        ],
        "frequency": "Weekly",
        "image": "http://jasonferruggia.com/wp-content/uploads/2017/09/Jmaes_Clear_400x400-270x270.jpg",
        "source": {
            "name": "3-2-1 Thursday",
            "url": "https://jamesclear.com/3-2-1"
        }
    },
    {
        "author": "Brian Dean, Josh Howarth",
        "description": "Exploding Topics scours the internet to find exploding trends before they take off. Each week we send you our best Exploding Topics. Plus, expert insight and analysis.",
        "categories": [
            "Internet"
        ],
        "frequency": "Weekly",
        "image": "https://pbs.twimg.com/profile_images/1208051900937101315/KiHstqqe_400x400.jpg",
        "source": {
            "name": "Exploding Topics",
            "url": "https://explodingtopics.com/newsletter"
        }
    },
    {
        "author": "Thomas Marban",
        "description": "3 interesting finds per day.",
        "categories": [
            "General"
        ],
        "frequency": "Daily",
        "image": "https://briefingday.com/static/20200318t082249/logo.svg",
        "source": {
            "name": "Briefingday",
            "url": "https://briefingday.com/"
        }
    },
    {
        "author": "Austin Kleon",
        "description": "Every week I send out a list of 10 things I think are worth sharing — new art, writing, and interesting links straight to your inbox.",
        "categories": [
            "Art"
        ],
        "frequency": "Weekly",
        "image": "https://austinkleon.com/wp-content/uploads/2018/09/kleon-200px.jpg",
        "source": {
            "name": "Newsletter",
            "url": "https://austinkleon.com/newsletter/"
        }
    },
    {
        "author": "Azeem Azhar",
        "description": "Azeem Azhar's weekly guide to the future.",
        "categories": [
            "Technology"
        ],
        "frequency": "Weekly",
        "image": "https://cdn.substack.com/image/fetch/w_170,c_limit,f_auto,q_auto:best/https%3A%2F%2Fbucketeer-e05bbc84-baa3-437e-9518-adb32be77984.s3.amazonaws.com%2Fpublic%2Fimages%2F03e96f1c-dc48-4b56-9cab-c69519c23c05_256x256",
        "source": {
            "name": "Exponential View",
            "url": "https://www.exponentialview.co/"
        }
    }
]